gazebo_yarp_synchronizer.libs/libACE-6-723764a8.3.3.so
gazebo_yarp_synchronizer.libs/libz-7fd423a0.so.1.2.8
gazebo_yarp_synchronizer-0.9.1.dist-info/LICENSE
gazebo_yarp_synchronizer-0.9.1.dist-info/METADATA
gazebo_yarp_synchronizer-0.9.1.dist-info/top_level.txt
gazebo_yarp_synchronizer-0.9.1.dist-info/RECORD
gazebo_yarp_synchronizer-0.9.1.dist-info/WHEEL
gazebo_yarp_synchronizer/__init__.py
gazebo_yarp_synchronizer/bindings.cpython-39-x86_64-linux-gnu.so
gazebo_yarp_synchronizer/lib/libGazeboYarpSynchronizer.a
gazebo_yarp_synchronizer/lib/libClockRpc.a
gazebo_yarp_synchronizer/lib/cmake/GazeboYarpSynchronizer/GazeboYarpSynchronizerConfigVersion.cmake
gazebo_yarp_synchronizer/lib/cmake/GazeboYarpSynchronizer/GazeboYarpSynchronizerConfig.cmake
gazebo_yarp_synchronizer/lib/cmake/GazeboYarpSynchronizer/GazeboYarpSynchronizerTargets-release.cmake
gazebo_yarp_synchronizer/lib/cmake/GazeboYarpSynchronizer/GazeboYarpSynchronizerTargets.cmake
gazebo_yarp_synchronizer/include/gys/GazeboYarpSynchronizer.h
