Metadata-Version: 2.1
Name: gazebo-yarp-synchronizer
Version: 0.9.1
Summary: Synchronization between Python and Gazebo Classic via YARP.
Home-page: https://github.com/diegoferigo/gazebo-synchronizer
Author: Diego Ferigo
Author-email: dgferigo@gmail.com
License: MIT
Project-URL: Changelog, https://github.com/diegoferigo/gazebo-synchronizer/releases
Project-URL: Tracker, https://github.com/diegoferigo/gazebo-synchronizer/issues
Project-URL: Source, https://github.com/diegoferigo/gazebo-synchronizer
Keywords: gazebo,gazebo classic,simulator,simulations,robot,robotics,yarp,plugins,synchronization,thrift,idl,clock
Platform: any
Classifier: Development Status :: 5 - Production/Stable
Classifier: Operating System :: OS Independent
Classifier: Operating System :: POSIX :: Linux
Classifier: Operating System :: MacOS
Classifier: Operating System :: Microsoft :: Windows
Classifier: Framework :: Robot Framework
Classifier: Topic :: Games/Entertainment :: Simulation
Classifier: Intended Audience :: Science/Research
Classifier: Intended Audience :: Developers
Classifier: Intended Audience :: Education
Classifier: Programming Language :: C++
Classifier: Programming Language :: Python :: 3
Classifier: Programming Language :: Python :: 3.7
Classifier: Programming Language :: Python :: 3.8
Classifier: Programming Language :: Python :: 3.9
Classifier: Programming Language :: Python :: 3 :: Only
Classifier: Programming Language :: Python :: Implementation :: CPython
Classifier: License :: OSI Approved :: MIT License
Requires-Python: >=3.7
License-File: LICENSE
